LICENSE.md
MANIFEST.in
README.md
setup.py
djangocms_googlecalendar/__init__.py
djangocms_googlecalendar/cms_plugins.py
djangocms_googlecalendar/models.py
djangocms_googlecalendar.egg-info/PKG-INFO
djangocms_googlecalendar.egg-info/SOURCES.txt
djangocms_googlecalendar.egg-info/dependency_links.txt
djangocms_googlecalendar.egg-info/not-zip-safe
djangocms_googlecalendar.egg-info/requires.txt
djangocms_googlecalendar.egg-info/top_level.txt
djangocms_googlecalendar/migrations/0001_initial.py
djangocms_googlecalendar/migrations/0002_auto_20171117_1901.py
djangocms_googlecalendar/migrations/__init__.py
djangocms_googlecalendar/static/djangocms_googlecalendar/fullcalendar-3.4.0/CHANGELOG.txt
djangocms_googlecalendar/static/djangocms_googlecalendar/fullcalendar-3.4.0/CONTRIBUTING.txt
djangocms_googlecalendar/static/djangocms_googlecalendar/fullcalendar-3.4.0/LICENSE.txt
djangocms_googlecalendar/static/djangocms_googlecalendar/fullcalendar-3.4.0/fullcalendar.css
djangocms_googlecalendar/static/djangocms_googlecalendar/fullcalendar-3.4.0/fullcalendar.js
djangocms_googlecalendar/static/djangocms_googlecalendar/fullcalendar-3.4.0/fullcalendar.min.css
djangocms_googlecalendar/static/djangocms_googlecalendar/fullcalendar-3.4.0/fullcalendar.min.js
djangocms_googlecalendar/static/djangocms_googlecalendar/fullcalendar-3.4.0/fullcalendar.print.css
djangocms_googlecalendar/static/djangocms_googlecalendar/fullcalendar-3.4.0/fullcalendar.print.min.css
djangocms_googlecalendar/static/djangocms_googlecalendar/fullcalendar-3.4.0/gcal.js
djangocms_googlecalendar/static/djangocms_googlecalendar/fullcalendar-3.4.0/gcal.min.js
djangocms_googlecalendar/static/djangocms_googlecalendar/fullcalendar-3.4.0/locale-all.js
djangocms_googlecalendar/static/djangocms_googlecalendar/fullcalendar-3.4.0/demos/agenda-views.html
djangocms_googlecalendar/static/djangocms_googlecalendar/fullcalendar-3.4.0/demos/background-events.html
djangocms_googlecalendar/static/djangocms_googlecalendar/fullcalendar-3.4.0/demos/basic-views.html
djangocms_googlecalendar/static/djangocms_googlecalendar/fullcalendar-3.4.0/demos/default.html
djangocms_googlecalendar/static/djangocms_googlecalendar/fullcalendar-3.4.0/demos/external-dragging.html
